[
    {
        "name": "德州黑椒卡尔香肠",
        "nmb": "555",
        "price": "44",
        "reason": "没有人拒绝香肠",
        "link": "/img/fun/sausages-3524649_1920.png"
    },
    {
        "name": "德州黑椒卡尔香肠",
        "nmb": "555",
        "price": "44",
        "reason": "没有人拒绝香肠",
        "link": "/img/fun/sausages-3524649_1920.png"
    },
    {
        "name": "德州黑椒卡尔香肠",
        "nmb": "555",
        "price": "44",
        "reason": "没有人拒绝香肠",
        "link": "/img/fun/sausages-3524649_1920.png"
    },
    {
        "name": "德州黑椒卡尔香肠",
        "nmb": "555",
        "price": "44",
        "reason": "没有人拒绝香肠",
        "link": "/img/fun/sausages-3524649_1920.png"
    }
]